docs/conf.py
kececinumbers/__init__.py
kececinumbers/_version.py
kececinumbers/kececinumbers.py
kececinumbers-0.9.1.dist-info/licenses/LICENSE
tests/test_helpers.py
tests/test_sample.py
kececinumbers-0.9.1.dist-info/METADATA
kececinumbers-0.9.1.dist-info/WHEEL
kececinumbers-0.9.1.dist-info/top_level.txt
kececinumbers-0.9.1.dist-info/RECORD
