Metadata-Version: 2.4
Name: kececinumbers
Version: 0.9.1
Summary: Keçeci Numbers: An Exploration of a Dynamic Sequence Across Diverse Number Sets
Home-page: https://github.com/WhiteSymmetry/kececinumbers
Author: Mehmet Keçeci
Author-email: Mehmet Keçeci <mkececi@yaani.com>
Maintainer: Mehmet Keçeci
Maintainer-email: mkececi@yaani.com
License:                     GNU AFFERO GENERAL PUBLIC LICENSE
Project-URL: Homepage, https://github.com/WhiteSymmetry/kececinumbers
Project-URL: Repository, https://github.com/WhiteSymmetry/kececinumbers
Classifier: Programming Language :: Python :: 3
Classifier: Operating System :: OS Independent
Classifier: Intended Audience :: Science/Research
Classifier: Topic :: Scientific/Engineering :: Visualization
Requires-Python: >=3.11
License-File: LICENSE
Requires-Dist: numpy
Requires-Dist: matplotlib
Requires-Dist: scipy
Requires-Dist: scikit-learn
Requires-Dist: sympy
Provides-Extra: test
Requires-Dist: pytest; extra == "test"
Requires-Dist: pytest-cov; extra == "test"
Requires-Dist: pytest-mock; extra == "test"
Requires-Dist: ruff; extra == "test"
Requires-Dist: numpy; extra == "test"
Requires-Dist: matplotlib; extra == "test"
Requires-Dist: scipy; extra == "test"
Requires-Dist: scikit-learn; extra == "test"
Requires-Dist: sympy; extra == "test"
Dynamic: author
Dynamic: home-page
Dynamic: license-file
Dynamic: maintainer
Dynamic: maintainer-email
Dynamic: requires-python
